{"bookmarked": 6, "bucket_name": "Today", "bucket_order": 3, "change_log": [{"anon": "stud", "data": "k2ik79lehul4sh", "type": "create", "uid_a": "a_0", "when": "2019-11-03T05:32:49Z"}, {"anon": "stud", "data": "k2ik7vhlap257c", "type": "update", "uid_a": "a_0", "when": "2019-11-03T05:33:17Z"}, {"anon": "no", "data": "k2il8ctm9lvjw", "to": "k2ik79lcyf64sg", "type": "s_answer", "uid": "j6ij45p75m92r7", "when": "2019-11-03T06:01:39Z"}, {"anon": "stud", "to": "k2ik79lcyf64sg", "type": "followup", "uid_a": "a_1", "when": "2019-11-03T22:25:50Z"}], "children": [{"bucket_name": "Today", "bucket_order": 3, "children": [], "config": {}, "created": "2019-11-03T06:01:39Z", "data": {"embed_links": []}, "folders": [], "history": [{"anon": "no", "content": "<p>Berkeley academic guide says it&#39;s webcasted</p>", "created": "2019-11-03T06:01:39Z", "subject": "", "uid": "j6ij45p75m92r7"}], "id": "k2il8ctdj7bjv", "is_tag_endorse": false, "tag_endorse": [], "tag_endorse_arr": [], "type": "s_answer"}, {"anon": "stud", "bucket_name": "Week 11/3 - 11/9", "bucket_order": 26, "children": [], "config": {}, "created": "2019-11-03T22:25:50Z", "data": {"embed_links": null}, "folders": [], "id": "k2jke0hngd3so", "no_answer": 1, "no_upvotes": 0, "subject": "<p>Also, if it&#39;s being webcasted is it possible to over-enroll?</p>", "tag_good": [], "tag_good_arr": [], "type": "followup", "uid_a": "a_1", "updated": "2019-11-03T22:25:50Z"}], "config": {}, "created": "2019-11-03T05:32:49Z", "data": {"embed_links": []}, "default_anonymity": "no", "drafts": null, "folders": ["other"], "history": [{"anon": "stud", "content": "<p>Is cs189 webcasted? It conflicts with my ballroom lessons and I\u2019d really need to take it next semester. Also why is it so late at night anyway?</p>", "created": "2019-11-03T05:33:17Z", "subject": "CS 189  webcasted?", "uid_a": "a_0"}, {"anon": "stud", "content": "<p>Is cs189 webcasted? It conflicts with my ballroom lessons and I\u2019d really need to take it next semester</p>", "created": "2019-11-03T05:32:49Z", "subject": "CS 189  webcasted?", "uid_a": "a_0"}], "i_edits": [], "id": "k2ik79lcyf64sg", "is_bookmarked": false, "is_tag_good": false, "my_favorite": false, "no_answer": 0, "no_answer_followup": 1, "nr": 10720, "num_favorites": 0, "q_edits": [], "request_instructor": 0, "request_instructor_me": false, "s_edits": [], "status": "active", "t": 1654545393618, "tag_good": [], "tag_good_arr": [], "tags": ["other", "student"], "type": "question", "unique_views": 331}