{"bookmarked": 5, "bucket_name": "Today", "bucket_order": 3, "change_log": [{"anon": "stud", "data": "k2js237d7gn4ns", "type": "create", "uid_a": "a_0", "when": "2019-11-04T02:00:30Z"}, {"anon": "no", "data": "k2jvie646zm649", "to": "k2js237ae8t4nr", "type": "s_answer", "uid": "j6nu587fjy94nn", "when": "2019-11-04T03:37:10Z"}], "children": [{"bucket_name": "Today", "bucket_order": 3, "children": [], "config": {}, "created": "2019-11-04T03:37:10Z", "data": {"embed_links": []}, "folders": [], "history": [{"anon": "no", "content": "<p>Yes, as long as you took 61A, 61B, 70.</p>", "created": "2019-11-04T03:37:10Z", "subject": "", "uid": "j6nu587fjy94nn"}], "id": "k2jvie5vm3x648", "is_tag_endorse": false, "tag_endorse": [], "tag_endorse_arr": [], "type": "s_answer"}], "config": {}, "created": "2019-11-04T02:00:30Z", "data": {"embed_links": []}, "default_anonymity": "no", "drafts": null, "folders": ["cs-intended"], "history": [{"anon": "stud", "content": "<p>Am I still eligible to declare CS if I took Math 55 before CS 70?</p>", "created": "2019-11-04T02:00:30Z", "subject": "CS Declaration", "uid_a": "a_0"}], "i_edits": [], "id": "k2js237ae8t4nr", "is_bookmarked": false, "is_tag_good": false, "my_favorite": false, "no_answer": 0, "no_answer_followup": 0, "nr": 10729, "num_favorites": 0, "q_edits": [], "request_instructor": 0, "request_instructor_me": false, "s_edits": [], "status": "active", "t": 1654545185009, "tag_good": [], "tag_good_arr": [], "tags": ["cs-intended", "student"], "type": "question", "unique_views": 392}