{"bookmarked": 5, "bucket_name": "Today", "bucket_order": 3, "change_log": [{"anon": "stud", "data": "k3hpc37zrh0764", "type": "create", "uid_a": "a_0", "when": "2019-11-27T19:48:28Z"}, {"anon": "stud", "data": "k3hpdc8m7pr143", "type": "update", "uid_a": "a_0", "when": "2019-11-27T19:49:26Z"}], "children": [], "config": {}, "created": "2019-11-27T19:48:28Z", "data": {"embed_links": []}, "default_anonymity": "no", "drafts": null, "folders": ["enrollments"], "history": [{"anon": "stud", "content": "<p>Is it really worth it to try to phase-2 CS189? The class is already full and the waitlist has 500 people in it. Would there even be a small chance for me to get in through the waitlist at this point? It seems that the class will only have 744 seats available and there are currently 900&#43; people trying to enroll.</p>", "created": "2019-11-27T19:49:26Z", "subject": "CS189 waitlist", "uid_a": "a_0"}, {"anon": "stud", "content": "<p>Is it really worth it to try to phase-2 CS189? The class is already full and the waitlist has 500 people in it. Would there even be a small chance for me to get in through the waitlist at this point?</p>", "created": "2019-11-27T19:48:28Z", "subject": "CS189 waitlist", "uid_a": "a_0"}], "i_edits": [], "id": "k3hpc37vazv763", "is_bookmarked": false, "is_tag_good": false, "my_favorite": false, "no_answer": 1, "no_answer_followup": 0, "nr": 10866, "num_favorites": 1, "q_edits": [], "request_instructor": 0, "request_instructor_me": false, "s_edits": [], "status": "active", "t": 1654545088624, "tag_good": [], "tag_good_arr": [], "tags": ["enrollments", "student", "unanswered"], "type": "question", "unique_views": 232}