{"bookmarked": 4, "bucket_name": "Today", "bucket_order": 3, "change_log": [{"anon": "stud", "data": "k8yw38tu1tu4ub", "type": "create", "uid_a": "a_0", "v": "all", "when": "2020-04-13T19:48:09Z"}], "children": [], "config": {}, "created": "2020-04-13T19:48:09Z", "data": {"embed_links": []}, "default_anonymity": "no", "drafts": null, "folders": ["enrollments"], "history": [{"anon": "stud", "content": "Hey! My friend and I are considering taking 162 in the Fall, and we were wondering if anyone else \u00a0planning on taking the class is looking for a group or teammates. Send me an email at shaviv&#64;berkeley.edu if you want to talk about it!", "created": "2020-04-13T19:48:09Z", "subject": "Anyone taking CS 162 in Fall 2020 looking for a group/teammates?", "uid_a": "a_0"}], "i_edits": [], "id": "k8yw38tsy9a4ua", "is_bookmarked": false, "is_tag_good": false, "my_favorite": false, "no_answer": 1, "no_answer_followup": 0, "nr": 11793, "num_favorites": 0, "q_edits": [], "request_instructor": 0, "request_instructor_me": false, "s_edits": [], "status": "active", "t": 1654544048383, "tag_good": [], "tag_good_arr": [], "tags": ["enrollments", "student", "unanswered"], "type": "question", "unique_views": 213}