{"bookmarked": 6, "bucket_name": "Today", "bucket_order": 3, "change_log": [{"anon": "stud", "data": "kdsnihqphg16tc", "type": "create", "uid_a": "a_0", "v": "all", "when": "2020-08-13T10:19:59Z"}, {"anon": "no", "data": "kdsrgt88eyi1s4", "to": "kdsnihqldr46tb", "type": "s_answer", "uid": "j6ij45p75m92r7", "when": "2020-08-13T12:10:39Z"}], "children": [{"bucket_name": "Today", "bucket_order": 3, "children": [], "config": {}, "created": "2020-08-13T12:10:39Z", "data": {"embed_links": []}, "folders": [], "history": [{"anon": "no", "content": "<p>Unless you signed up to take the unit over the summer (which most people don&#39;t do) you&#39;ll be enrolled in a class for Fall 2020 which you&#39;ll automatically pass, after which you&#39;ll get the unit at the end of the semester\u00a0</p>", "created": "2020-08-13T12:10:39Z", "subject": "", "uid": "j6ij45p75m92r7"}], "id": "kdsrgt7yp9z1s3", "is_tag_endorse": false, "tag_endorse": [], "tag_endorse_arr": [], "type": "s_answer"}], "config": {"seen": {"12505": 3, "4077": 0, "4317": 8, "4321": 1, "649": 4, "6709": 9, "8404": 6, "9132": 5, "9239": 7, "9920": 2}}, "created": "2020-08-13T10:19:59Z", "data": {"embed_links": []}, "default_anonymity": "no", "drafts": null, "folders": ["other"], "history": [{"anon": "stud", "content": "<p>Since the credit is deferred to fall, will it be shown at the end of summer semester, before fall semester, or at the end of fall semester? Thanks for any response!</p>", "created": "2020-08-13T10:19:59Z", "subject": "Does anyone know when will the grade for summer cs61bl AI be reflected in CalCentral?", "uid_a": "a_0"}], "i_edits": [], "id": "kdsnihqldr46tb", "is_bookmarked": false, "is_tag_good": false, "my_favorite": false, "no_answer": 0, "no_answer_followup": 0, "nr": 12877, "num_favorites": 0, "q_edits": [], "request_instructor": 0, "request_instructor_me": false, "s_edits": [], "status": "active", "t": 1654542839994, "tag_good": [], "tag_good_arr": [], "tags": ["other", "student"], "type": "question", "unique_views": 373}