{"bookmarked": 7, "bucket_name": "Today", "bucket_order": 3, "change_log": [{"anon": "stud", "data": "kggviogsojx4e5", "type": "create", "uid_a": "a_0", "v": "all", "when": "2020-10-19T18:29:57Z"}, {"anon": "stud", "data": "kggvyqyjj1w74a", "to": "kggviogo6kp4e4", "type": "s_answer", "uid_a": "a_1", "when": "2020-10-19T18:42:27Z"}], "children": [{"bucket_name": "Today", "bucket_order": 3, "children": [], "config": {}, "created": "2020-10-19T18:42:27Z", "data": {"embed_links": []}, "folders": [], "history": [{"anon": "stud", "content": "<p>@12414 and <a href=\"https://eecs.berkeley.edu/resources/undergrads/cs/degree-reqs-lowerdiv\" target=\"_blank\" rel=\"noopener noreferrer\">https://eecs.berkeley.edu/resources/undergrads/cs/degree-reqs-lowerdiv</a> have lots of great advice!\u00a0</p>", "created": "2020-10-19T18:42:27Z", "subject": "", "uid_a": "a_1"}], "id": "kggvyqy89pz749", "is_tag_endorse": false, "tag_endorse": [], "tag_endorse_arr": [], "type": "s_answer"}], "config": {"seen": {"10031": 3, "10667": 7, "11072": 8, "12336": 2, "4469": 4, "4773": 6, "4807": 9, "6217": 5, "6518": 1, "9155": 0}}, "created": "2020-10-19T18:29:57Z", "data": {"embed_links": []}, "default_anonymity": "no", "drafts": null, "folders": ["peer_directed", "lscs", "enrollments"], "history": [{"anon": "stud", "content": "<p>Would people recommend to take 16A to prepare for 16B if I have already taken Math 54? Or would it be a better choice to just self study the circuit portion of 16A to prepare for EE16b?</p>", "created": "2020-10-19T18:29:57Z", "subject": "EE16B with just Math 54?", "uid_a": "a_0"}], "i_edits": [], "id": "kggviogo6kp4e4", "is_bookmarked": false, "is_tag_good": false, "my_favorite": false, "no_answer": 0, "no_answer_followup": 0, "nr": 13412, "num_favorites": 0, "q_edits": [], "request_instructor": 0, "request_instructor_me": false, "s_edits": [], "status": "active", "t": 1654542252986, "tag_good": [], "tag_good_arr": [], "tags": ["enrollments", "lscs", "peer_directed", "student"], "type": "question", "unique_views": 253}