{"bookmarked": 10, "bucket_name": "Today", "bucket_order": 3, "change_log": [{"anon": "stud", "data": "ki6cb6686ca595", "type": "create", "uid_a": "a_0", "v": "all", "when": "2020-12-01T18:53:57Z"}, {"anon": "no", "data": "ki7sfwx29tk1qu", "to": "ki6cb664jfd594", "type": "i_answer", "uid": "h87kastcacfxt", "when": "2020-12-02T19:13:18Z"}], "children": [{"bucket_name": "Today", "bucket_order": 3, "children": [], "config": {}, "created": "2020-12-02T19:13:18Z", "data": {"embed_links": []}, "folders": [], "history": [{"anon": "no", "content": "<p>When a faculty member or an employer looks at a P, they think that you could have gotten anything between an A and a C-. A B or a B&#43; is a whole lot better than a C-. I&#39;d be inclined to leave the grade there.</p>", "created": "2020-12-02T19:13:18Z", "subject": "", "uid": "h87kastcacfxt"}], "history_size": 1, "id": "ki7sfwwsnuj1qt", "is_tag_endorse": false, "tag_endorse": [], "tag_endorse_arr": [], "type": "i_answer"}], "config": {"seen": {"10890": 7, "11267": 4, "11548": 1, "11615": 3, "12772": 2, "13623": 0, "13624": 5, "13692": 8, "4568": 9, "6947": 6}}, "created": "2020-12-01T18:53:57Z", "data": {"embed_links": []}, "default_anonymity": "no", "drafts": null, "folders": ["eecs"], "history": [{"anon": "stud", "content": "<p>Hi,</p>\n<p></p>\n<p>I have a general question. For CS61A and EECS16A is it better to take them p/np or get B/ B&#43;? I would like to know how bad B or B&#43; is in compare with p. (For EECS students)</p>", "created": "2020-12-01T18:53:57Z", "subject": "P/ NP for CS61A and EECS16A", "uid_a": "a_0"}], "history_size": 1, "i_edits": [], "id": "ki6cb664jfd594", "is_bookmarked": false, "is_tag_good": false, "my_favorite": false, "no_answer": 0, "no_answer_followup": 0, "nr": 13814, "num_favorites": 0, "q_edits": [], "request_instructor": 0, "request_instructor_me": false, "s_edits": [], "status": "active", "t": 1654541809355, "tag_good": [], "tag_good_arr": [], "tags": ["eecs", "student"], "type": "question", "unique_views": 308}