{"bookmarked": 4, "bucket_name": "Today", "bucket_order": 3, "change_log": [{"anon": "stud", "data": "iugog9jkmc85bl", "type": "create", "uid_a": "a_0", "when": "2016-10-19T08:49:12Z"}, {"anon": "no", "data": "iuh3m1lak5jpg", "to": "iugog9jhxea5bk", "type": "i_answer", "uid": "icdxydvnk125h8", "when": "2016-10-19T15:53:36Z"}], "children": [{"bucket_name": "Today", "bucket_order": 3, "children": [], "config": {}, "created": "2016-10-19T15:53:36Z", "data": {"embed_links": []}, "folders": [], "history": [{"anon": "no", "content": "<p>Please search old questions. This has been answered a few times on here.\u00a0</p>", "created": "2016-10-19T15:53:36Z", "subject": "", "uid": "icdxydvnk125h8"}], "id": "iuh3m1l58sxpf", "is_tag_endorse": false, "tag_endorse": [], "tag_endorse_arr": [], "type": "i_answer"}], "config": {}, "created": "2016-10-19T08:49:12Z", "data": {"embed_links": []}, "default_anonymity": "no", "drafts": {}, "folders": ["eecs", "cs", "enrollments"], "history": [{"anon": "stud", "content": "<p>I want to take CS 268. Is there any prerequisite or permission that I need? I cannot directly enroll from Cal Central. It says &#39;Permission to enroll is required&#39;.\u00a0</p>", "created": "2016-10-19T08:49:12Z", "subject": "How do I enroll in graduate CS courses?", "uid_a": "a_0"}], "i_edits": [], "id": "iugog9jhxea5bk", "is_bookmarked": false, "is_tag_good": false, "my_favorite": false, "no_answer": 0, "no_answer_followup": 0, "nr": 2377, "num_favorites": 0, "q_edits": [], "request_instructor": 0, "request_instructor_me": false, "s_edits": [], "status": "active", "t": 1654554315391, "tag_good": [], "tag_good_arr": [], "tags": ["cs", "eecs", "enrollments", "student"], "type": "question", "unique_views": 236}