{"bookmarked": 4, "bucket_name": "Today", "bucket_order": 3, "change_log": [{"anon": "full", "data": "iukkuannmfx4hf", "type": "create", "uid_a": "a_0", "when": "2016-10-22T02:19:13Z"}, {"anon": "full", "to": "iukkuanlp4t4he", "type": "followup", "uid_a": "a_0", "when": "2016-10-22T02:21:15Z"}, {"anon": "full", "to": "iukkuanlp4t4he", "type": "feedback", "uid_a": "a_1", "when": "2016-10-22T05:02:00Z"}, {"anon": "full", "data": "iulgxyjkfp76u3", "to": "iukkuanlp4t4he", "type": "s_answer", "uid_a": "a_2", "when": "2016-10-22T17:17:51Z"}], "children": [{"anon": "full", "bucket_name": "Week 10/16 - 10/22", "bucket_order": 189, "children": [{"anon": "full", "bucket_name": "Week 10/16 - 10/22", "bucket_order": 189, "children": [], "config": {}, "created": "2016-10-22T05:02:00Z", "data": {"embed_links": null}, "folders": [], "id": "iukqnmvzzxr6tb", "subject": "Unfortunately, it does not.\u00a0", "tag_good": [], "tag_good_arr": [], "type": "feedback", "uid_a": "a_1", "updated": "2016-10-22T05:02:00Z"}], "config": {}, "created": "2016-10-22T02:21:15Z", "data": {"embed_links": null}, "folders": [], "id": "iukkwwoyavq2oo", "no_answer": 0, "no_upvotes": 0, "subject": "<p>Does <em>CS 195: Social Implications of Computer Science</em> count as an upper-div?</p>", "tag_good": [], "tag_good_arr": [], "type": "followup", "uid_a": "a_0", "updated": "2016-10-22T02:21:15Z"}, {"bucket_name": "Today", "bucket_order": 3, "children": [], "config": {}, "created": "2016-10-22T17:17:51Z", "data": {"embed_links": []}, "folders": [], "history": [{"anon": "full", "content": "<p>You could look here:\u00a0http://guide.berkeley.edu/courses/compsci/</p>", "created": "2016-10-22T17:17:51Z", "subject": "", "uid_a": "a_2"}], "id": "iulgxyjep636u2", "is_tag_endorse": false, "tag_endorse": [], "tag_endorse_arr": [], "type": "s_answer"}], "config": {}, "created": "2016-10-22T02:19:13Z", "data": {"embed_links": []}, "default_anonymity": "no", "drafts": {}, "folders": ["eecs"], "history": [{"anon": "full", "content": "<p>In the college of Engineering, and am a few units short of the minimum req. units.\u00a0</p>\n<p></p>\n<p>Are there any upper-div courses that are less than 4 units?</p>", "created": "2016-10-22T02:19:13Z", "subject": "Are there any 1 or 2 unit CS courses that count as upper-div?", "uid_a": "a_0"}], "i_edits": [], "id": "iukkuanlp4t4he", "is_bookmarked": false, "is_tag_good": false, "my_favorite": false, "no_answer": 0, "no_answer_followup": 0, "nr": 2419, "num_favorites": 0, "q_edits": [], "request_instructor": 0, "request_instructor_me": false, "s_edits": [], "status": "active", "t": 1654554361745, "tag_good": [], "tag_good_arr": [], "tags": ["eecs", "student"], "type": "question", "unique_views": 258}