{"bookmarked": 3, "bucket_name": "Today", "bucket_order": 3, "change_log": [{"anon": "full", "data": "iusue5pxoah781", "type": "create", "uid_a": "a_0", "when": "2016-10-27T21:08:45Z"}, {"anon": "full", "data": "iusvh04fk6qdm", "to": "iusue5pt8el780", "type": "s_answer", "uid_a": "a_1", "when": "2016-10-27T21:38:58Z"}], "children": [{"bucket_name": "Today", "bucket_order": 3, "children": [], "config": {}, "created": "2016-10-27T21:38:58Z", "data": {"embed_links": []}, "folders": [], "history": [{"anon": "full", "content": "<p>No guarantees can be made, you should Phase I if you really want to get in.</p>", "created": "2016-10-27T21:38:58Z", "subject": "", "uid_a": "a_1"}], "id": "iusvh04arb8dl", "is_tag_endorse": false, "tag_endorse": [], "tag_endorse_arr": [], "type": "s_answer"}], "config": {}, "created": "2016-10-27T21:08:45Z", "data": {"embed_links": []}, "default_anonymity": "no", "drafts": {}, "folders": ["cs"], "history": [{"anon": "full", "content": "As an L&amp;S intended CS major, is it safe to phase 2 cs70?", "created": "2016-10-27T21:08:45Z", "subject": "CS70 Phase 2", "uid_a": "a_0"}], "i_edits": [], "id": "iusue5pt8el780", "is_bookmarked": false, "is_tag_good": false, "my_favorite": false, "no_answer": 0, "no_answer_followup": 0, "nr": 2518, "num_favorites": 1, "q_edits": [], "request_instructor": 0, "request_instructor_me": false, "s_edits": [], "status": "active", "t": 1654554195131, "tag_good": [], "tag_good_arr": [], "tags": ["cs", "student"], "type": "question", "unique_views": 223}