{"bookmarked": 3, "bucket_name": "Today", "bucket_order": 3, "change_log": [{"anon": "full", "data": "ix2bf2fjl5n3n3", "type": "create", "uid_a": "a_0", "when": "2016-12-23T21:34:41Z"}, {"anon": "no", "data": "ix2dtsj9rs27q", "to": "ix2bf2figqg3n2", "type": "s_answer", "uid": "hz5sgwoz18fhu", "when": "2016-12-23T22:42:08Z"}, {"anon": "no", "to": "ix2bf2figqg3n2", "type": "followup", "uid": "idgojx8xjdn40y", "when": "2016-12-27T06:08:32Z"}, {"anon": "full", "to": "ix2bf2figqg3n2", "type": "feedback", "uid_a": "a_0", "when": "2016-12-27T06:35:03Z"}, {"anon": "no", "to": "ix2bf2figqg3n2", "type": "feedback", "uid": "idgojx8xjdn40y", "when": "2016-12-27T06:54:45Z"}], "children": [{"bucket_name": "Today", "bucket_order": 3, "children": [], "config": {}, "created": "2016-12-23T22:42:08Z", "data": {"embed_links": []}, "folders": [], "history": [{"anon": "no", "content": "<p>Might be too hard. 170 and 126 are very heavy theoretical courses, and if CS 70 wasn&#39;t a cakewalk for you, both of these courses in together will be really difficult. ?None of those courses have huge projects (CS 170 has a final project at the end, but it&#39;s not too time consuming).</p>\n<p></p>\n<p>CS 188 is also pretty heavy theory, but I don&#39;t think it would be as troublesome as 170 or 126. Projects are pretty easy, and all assignments are edX, so workload-wise it&#39;s not too bad. However, studying for exams might be a bit hard.\u00a0</p>\n<p></p>\n<p>CS 61C is another beast altogether. There&#39;s a couple of projects (CPU and Assembler) that are very difficult. However, the other ones are pretty manageable. Content is a hit or miss: if you&#39;re good at CS 70-like courses, I think it&#39;ll be the hardest course on your list. If you don&#39;t find theory easy, then I&#39;d put it between CS 188 and CS 170/EE 126 in terms of difficulty.\u00a0</p>\n<p></p>\n<p>If you&#39;re pretty strong with theory courses, I&#39;d reserve CS 61C for another semester when your course load is lighter. If not, definitely put off EE 126 or CS 170 for some other semester.</p>", "created": "2016-12-23T22:42:08Z", "subject": "", "uid": "hz5sgwoz18fhu"}], "id": "ix2dtsj2rb37p", "is_tag_endorse": false, "tag_endorse": [], "tag_endorse_arr": [], "type": "s_answer"}, {"anon": "no", "bucket_name": "Week 12/25 - 12/31", "bucket_order": 176, "children": [{"anon": "full", "bucket_name": "Week 12/25 - 12/31", "bucket_order": 176, "children": [], "config": {}, "created": "2016-12-27T06:35:03Z", "data": {"embed_links": null}, "folders": [], "id": "ix751j8yi837ge", "subject": "<p>Do you have a death wish?</p>", "tag_good": [], "tag_good_arr": [], "type": "feedback", "uid_a": "a_0", "updated": "2016-12-27T06:35:03Z"}, {"anon": "no", "bucket_name": "Week 12/25 - 12/31", "bucket_order": 176, "children": [], "config": {}, "created": "2016-12-27T06:54:45Z", "data": {"embed_links": null}, "folders": [], "id": "ix75quugmz838z", "subject": "<p>we&#39;re gonna win bigly, it&#39;s gonna fantastik, huuge, it&#39;s called the world of winning and success.</p>", "tag_good": [], "tag_good_arr": [], "type": "feedback", "uid": "idgojx8xjdn40y", "updated": "2016-12-27T06:54:45Z"}], "config": {}, "created": "2016-12-27T06:08:32Z", "data": {"embed_links": null}, "folders": [], "id": "ix743f6f6w6369", "no_answer": 0, "no_upvotes": 0, "subject": "<p>This is a message I gave to another student a few days back on piazza:</p>\n<p></p>\n<p>Whatever you decide to do, make sure to assess your personal abilities very well, and I don&#39;t get too carried away with what others have to say. Make sure that only you are your number one source of decision making, not other students on Piazza. I made the mistake of only taking 3 classes this semester (all of which were techs), because several students on Piazza told me that 4 techs would be too heavy. Well..it turned out to be a boring and somewhat uninspiring semester. So next semester I&#39;m going for 5 or 6 classes. People are now urging me to not do this, but at this point I have assessed my capabilities well enough to trust myself.</p>", "tag_good": [], "tag_good_arr": [], "type": "followup", "uid": "idgojx8xjdn40y", "updated": "2016-12-27T06:08:32Z"}], "config": {}, "created": "2016-12-23T21:34:41Z", "data": {"embed_links": []}, "default_anonymity": "no", "drafts": {}, "folders": ["cs", "suggestion_box"], "history": [{"anon": "full", "content": "<p>I am planning to take these courses next semester.</p>\n<p>Is it doable? Many\u00a0people say no. If not, what are the main challenges I will face (overlapping projects, etc).</p>", "created": "2016-12-23T21:34:41Z", "subject": "Is EE 126, CS 188, CS 170, CS 61C too much?", "uid_a": "a_0"}], "i_edits": [], "id": "ix2bf2figqg3n2", "is_bookmarked": false, "is_tag_good": false, "my_favorite": false, "no_answer": 0, "no_answer_followup": 0, "nr": 2893, "num_favorites": 1, "q_edits": [], "request_instructor": 0, "request_instructor_me": false, "s_edits": [], "status": "active", "t": 1654553771740, "tag_good": [], "tag_good_arr": [], "tags": ["cs", "student", "suggestion_box"], "type": "question", "unique_views": 366}