{"bookmarked": 6, "bucket_name": "Today", "bucket_order": 3, "change_log": [{"anon": "no", "data": "j3m7tnflpcyqf", "type": "create", "uid": "ib1dv67kzjj12t", "when": "2017-06-06T23:47:41Z"}, {"anon": "no", "data": "j3m7xgndrkl1y1", "to": "j3m7tnfhkr1qe", "type": "i_answer", "uid": "icdxydvnk125h8", "when": "2017-06-06T23:50:39Z"}, {"anon": "no", "data": "j3m7y0285my4cv", "type": "i_answer_update", "uid": "icdxydvnk125h8", "when": "2017-06-06T23:51:04Z"}, {"anon": "no", "data": "j3m84wx35vj6e7", "type": "update", "uid": "ib1dv67kzjj12t", "when": "2017-06-06T23:56:26Z"}, {"anon": "no", "data": "j3mgrenq5v834c", "type": "i_answer_update", "uid": "i1i1qn178di2vn", "when": "2017-06-07T03:57:53Z"}, {"anon": "no", "to": "j3m7tnfhkr1qe", "type": "followup", "uid": "is6p771gx0l5yd", "when": "2017-06-26T20:43:46Z"}, {"anon": "no", "to": "j3m7tnfhkr1qe", "type": "dupe", "uid": "h69mwtr4j7461h", "when": "2017-06-26T20:43:46Z"}], "children": [{"bucket_name": "Today", "bucket_order": 3, "children": [], "config": {}, "created": "2017-06-06T23:50:39Z", "data": {"embed_links": []}, "folders": [], "history": [{"anon": "no", "content": "<p>CS\u00a0courses always have some seats reserved (30%) until GSI hiring is done. &#64;3831 (see point #1)</p>", "created": "2017-06-07T03:57:53Z", "subject": "", "uid": "i1i1qn178di2vn"}, {"anon": "no", "content": "<p>CS\u00a0courses always have some seats reserved (30%) until GSI hiring is done. &#64;3831</p>\n<p></p>\n<p>You also didn&#39;t specify if you&#39;re declared or not. This matters</p>", "created": "2017-06-06T23:51:04Z", "subject": "", "uid": "icdxydvnk125h8"}, {"anon": "no", "content": "<p>CS\u00a0courses always have some seats reserved (30%) until GSI hiring is done. You also didn&#39;t specify if you&#39;re declared or not.\u00a0</p>", "created": "2017-06-06T23:50:39Z", "subject": "", "uid": "icdxydvnk125h8"}], "id": "j3m7xgn6u1y0", "is_tag_endorse": false, "tag_endorse": [], "tag_endorse_arr": [], "type": "i_answer"}, {"anon": "no", "bucket_name": "Week 6/25 - 7/1", "bucket_order": 150, "children": [{"anon": "no", "bucket_name": "Week 6/25 - 7/1", "bucket_order": 150, "children": [], "config": {}, "created": "2017-06-26T20:43:46Z", "data": {"embed_links": null}, "folders": [], "id": "j4em26f27b636h", "subject": "", "type": "dupe", "uid": "h69mwtr4j7461h", "updated": "2017-06-26T20:43:46Z"}], "config": {}, "created": "2017-06-26T20:43:46Z", "data": {"embed_links": null}, "folders": [], "id": "j4em26deanb36g", "no_answer": 0, "no_upvotes": 0, "subject": "Can&#39;t enroll in 170?\n<p>Hi, I received an email earlier saying I&#39;ve successfully declared CS. I tried to add CS 170 for the fall, but CalCentral\u00a0still won&#39;t let me. It says I don&#39;t meet the reserved seat requirements, and I&#39;m 183 on the waitlist.</p>\n<p>Why\u00a0am I still unable to enroll, even though I&#39;m declared?</p>", "tag_good": [], "tag_good_arr": [], "type": "followup", "uid": "is6p771gx0l5yd", "updated": "2017-06-26T20:43:46Z"}], "config": {}, "created": "2017-06-06T23:47:41Z", "data": {"embed_links": []}, "default_anonymity": "no", "drafts": null, "folders": ["cs", "enrollments"], "history": [{"anon": "no", "content": "<p>I signed up for 168 since it appeared to have open seats but ended up on the waitlist because apparently all 153 (???) of the open seats are &#34;reserved for Enrollment by Permission Only&#34;. Does anyone know why a third of the seats are reserved and who exactly is able to get &#34;permission&#34;?</p>\n<p></p>\n<p>EDIT: I am a senior declared L&amp;S CS Major, for context</p>", "created": "2017-06-06T23:56:26Z", "subject": "CS168 reserved seats?", "uid": "ib1dv67kzjj12t"}, {"anon": "no", "content": "<p>I signed up for 168 since it appeared to have open seats but ended up on the waitlist because apparently all 153 (???) of the open seats are &#34;reserved for Enrollment by Permission Only&#34;. Does anyone know why a third of the seats are reserved and who exactly is able to get &#34;permission&#34;?</p>", "created": "2017-06-06T23:47:41Z", "subject": "CS168 reserved seats?", "uid": "ib1dv67kzjj12t"}], "i_edits": [], "id": "j3m7tnfhkr1qe", "is_bookmarked": false, "is_tag_good": false, "my_favorite": false, "no_answer": 0, "no_answer_followup": 0, "nr": 4366, "num_favorites": 0, "q_edits": [], "request_instructor": 0, "request_instructor_me": false, "s_edits": [], "status": "active", "t": 1654551956446, "tag_good": [], "tag_good_arr": [], "tags": ["cs", "enrollments", "student"], "type": "question", "unique_views": 382}