{"bookmarked": 3, "bucket_name": "Today", "bucket_order": 3, "change_log": [{"anon": "stud", "data": "j54at0dn1hd4uu", "type": "create", "uid_a": "a_0", "when": "2017-07-14T20:10:43Z"}, {"anon": "no", "data": "j54bn38tgtr2ih", "to": "j54at0djb7u4ut", "type": "i_answer", "uid": "icdxydvnk125h8", "when": "2017-07-14T20:34:07Z"}], "children": [{"bucket_name": "Today", "bucket_order": 3, "children": [], "config": {}, "created": "2017-07-14T20:34:07Z", "data": {"embed_links": []}, "folders": [], "history": [{"anon": "no", "content": "<p>Please contact this team:\u00a0<a href=\"https://acropolis.cs.berkeley.edu/~account/webacct/\">https://acropolis.cs.berkeley.edu/~account/webacct/</a>\u00a0This is not controlled by Advisors</p>", "created": "2017-07-14T20:34:07Z", "subject": "", "uid": "icdxydvnk125h8"}], "id": "j54bn364mdn2ig", "is_tag_endorse": false, "tag_endorse": [], "tag_endorse_arr": [], "type": "i_answer"}], "config": {}, "created": "2017-07-14T20:10:43Z", "data": {"embed_links": []}, "default_anonymity": "no", "drafts": null, "folders": ["cs", "policy"], "history": [{"anon": "stud", "content": "<p>Hi, is it possible fore CS majors who are not enrolled in a CS class over summer to get an instructional account?\u00a0</p>", "created": "2017-07-14T20:10:43Z", "subject": "Instructional Account", "uid_a": "a_0"}], "i_edits": [], "id": "j54at0djb7u4ut", "is_bookmarked": false, "is_tag_good": false, "my_favorite": false, "no_answer": 0, "no_answer_followup": 0, "nr": 4513, "num_favorites": 1, "q_edits": [], "request_instructor": 0, "request_instructor_me": false, "s_edits": [], "status": "active", "t": 1654551831162, "tag_good": [], "tag_good_arr": [], "tags": ["cs", "policy", "student"], "type": "question", "unique_views": 379}