{"bookmarked": 4, "bucket_name": "Today", "bucket_order": 3, "change_log": [{"anon": "stud", "data": "j6wsjoka9q05nv", "type": "create", "uid_a": "a_0", "when": "2017-08-28T23:24:37Z"}, {"anon": "no", "data": "j6wt567za6num", "to": "j6wsjok6coa5nu", "type": "i_answer", "uid": "icdxydvnk125h8", "when": "2017-08-28T23:41:19Z"}, {"anon": "stud", "to": "j6wsjok6coa5nu", "type": "followup", "uid_a": "a_0", "when": "2017-08-28T23:47:39Z"}, {"anon": "no", "to": "j6wsjok6coa5nu", "type": "feedback", "uid": "h69mwtr4j7461h", "when": "2017-08-28T23:49:58Z"}, {"anon": "stud", "to": "j6wsjok6coa5nu", "type": "feedback", "uid_a": "a_0", "when": "2017-08-28T23:50:40Z"}], "children": [{"bucket_name": "Today", "bucket_order": 3, "children": [], "config": {}, "created": "2017-08-28T23:41:19Z", "data": {"embed_links": []}, "folders": [], "history": [{"anon": "no", "content": "<p>please read the pinned post.</p>", "created": "2017-08-28T23:41:19Z", "subject": "", "uid": "icdxydvnk125h8"}], "history_size": 1, "id": "j6wt56793fzuk", "is_tag_endorse": false, "tag_endorse": [], "tag_endorse_arr": [], "type": "i_answer"}, {"anon": "stud", "bucket_name": "Week 8/27 - 9/2", "bucket_order": 186, "children": [{"anon": "no", "bucket_name": "Week 8/27 - 9/2", "bucket_order": 186, "children": [], "config": {}, "created": "2017-08-28T23:49:58Z", "data": {"embed_links": null}, "folders": [], "id": "j6wtga7wdav2ck", "subject": "<p>If you want to use the enrollment system&#39;s conflict form, it only shows up when you try to enroll in a conflicting class. So, you&#39;ll have to drop one of the two and reenroll.</p>\n<p></p>\n<p>You can try talking to the stats department to see if their department staff is willing to do\u00a0additional manual work to enroll you, like the CS/EECS department is doing.</p>", "tag_good": [], "tag_good_arr": [], "type": "feedback", "uid": "h69mwtr4j7461h", "updated": "2017-08-28T23:49:58Z"}, {"anon": "stud", "bucket_name": "Week 8/27 - 9/2", "bucket_order": 186, "children": [], "config": {}, "created": "2017-08-28T23:50:40Z", "data": {"embed_links": null}, "folders": [], "id": "j6wth75en82u2", "subject": "<p>Thanks!</p>", "tag_good": [], "tag_good_arr": [], "type": "feedback", "uid_a": "a_0", "updated": "2017-08-28T23:50:40Z"}], "config": {}, "created": "2017-08-28T23:47:39Z", "data": {"embed_links": null}, "folders": [], "id": "j6wtdbb92nc2we", "no_answer": 0, "no_upvotes": 0, "subject": "<p>I saw that. The classes Im having conflicts with are stats classes. Do I need to go to the stats dept for this?</p>", "tag_good": [], "tag_good_arr": [], "type": "followup", "uid_a": "a_0", "updated": "2017-08-28T23:47:39Z"}], "config": {}, "created": "2017-08-28T23:24:37Z", "data": {"embed_links": []}, "default_anonymity": "no", "drafts": null, "folders": ["enrollments"], "history": [{"anon": "stud", "content": "<p>Im currently waitlisted for a class (although there&#39;s enough room). I asked the professor why I haven&#39;t been enrolled and he said its because of a conflict. My lab section is conflicting with another lecture. I can&#39;t seem to find a conflict form on my cal central. Where is the link? Has it moved?</p>", "created": "2017-08-28T23:24:37Z", "subject": "Conflict form", "uid_a": "a_0"}], "history_size": 1, "i_edits": [], "id": "j6wsjok6coa5nu", "is_bookmarked": false, "is_tag_good": false, "my_favorite": false, "no_answer": 0, "no_answer_followup": 0, "nr": 4901, "num_favorites": 0, "q_edits": [], "request_instructor": 0, "request_instructor_me": false, "s_edits": [], "status": "active", "t": 1654551419029, "tag_good": [], "tag_good_arr": [], "tags": ["enrollments", "student"], "type": "question", "unique_views": 266}