{"bookmarked": 2, "bucket_name": "Today", "bucket_order": 3, "change_log": [{"anon": "no", "data": "ja8fqjmo58117b", "type": "create", "uid": "icdxydvnk125h8", "when": "2017-11-20T16:58:23Z"}], "children": [], "config": {}, "created": "2017-11-20T16:58:23Z", "data": {"embed_links": []}, "default_anonymity": "no", "drafts": null, "folders": ["announcements"], "history": [{"anon": "no", "content": "<p></p><div>\n<div>We are currently seeking students to serve as a Reader and grade work for the course\u00a0<b>this semester</b>.\u00a0</div>\n<div></div>\n<div>Requirements:</div>\n<ol><li>Must be registered at UC Berkeley\u00a0this semester.</li><li>Overall GPA of 3.0 or higher, and maintain this GPA during the semester you are teaching</li><li>Have previously taken the course, its equivalent or a more advanced course,\u00a0<em>with a grade of B or better</em></li></ol>\n<div></div>\n<div></div>\n<div>If you are interested and available 9 to 20 hours per week (probably through finals week?), please email me and copy Professor\u00a0Wu (wu&#64;eecs.berkeley.edu)</div>\n<div><br /><br /></div>\n</div>", "created": "2017-11-20T16:58:23Z", "subject": "Seeking Paid EE 105 Reader for remainder of semester", "uid": "icdxydvnk125h8"}], "history_size": 1, "i_edits": [], "id": "ja8fqjml8ym17a", "is_bookmarked": false, "is_tag_good": false, "my_favorite": false, "no_answer_followup": 0, "nr": 5597, "num_favorites": 0, "q_edits": [], "request_instructor": 0, "request_instructor_me": false, "s_edits": [], "status": "active", "t": 1654550714646, "tag_good": [], "tag_good_arr": [], "tags": ["announcements", "instructor-note"], "type": "note", "unique_views": 340}