{"bookmarked": 7, "bucket_name": "Today", "bucket_order": 3, "change_log": [{"anon": "stud", "data": "jv384jtc3y5we", "type": "create", "uid_a": "a_0", "when": "2019-04-30T03:20:18Z"}, {"anon": "stud", "data": "jv384z6nyza6ca", "type": "update", "uid_a": "a_0", "when": "2019-04-30T03:20:37Z"}, {"anon": "no", "to": "jv384jt6bzi5wd", "type": "followup", "uid": "ijbyyqoowfj720", "when": "2019-04-30T03:31:34Z"}, {"anon": "stud", "to": "jv384jt6bzi5wd", "type": "feedback", "uid_a": "a_1", "when": "2019-04-30T03:47:14Z"}, {"anon": "stud", "to": "jv384jt6bzi5wd", "type": "feedback", "uid_a": "a_0", "when": "2019-04-30T05:39:19Z"}, {"anon": "stud", "to": "jv384jt6bzi5wd", "type": "feedback", "uid_a": "a_1", "when": "2019-04-30T18:32:23Z"}], "children": [{"anon": "no", "bucket_name": "Week 4/28 - 5/4", "bucket_order": 47, "children": [{"anon": "stud", "bucket_name": "Week 4/28 - 5/4", "bucket_order": 47, "children": [], "config": {}, "created": "2019-04-30T03:47:14Z", "data": {"embed_links": null}, "folders": [], "id": "jv3936xwj3h7ko", "subject": "Agreed 100% ^. I took all 3 and is currently in Shewchuk\u2019s 189. I think just spending extra time on Shewchuk\u2019s 189 will be good enough. There are plenty of algorithmic/coding assignments that will be enjoyable even for mild ML interest only!", "tag_good": [], "tag_good_arr": [], "type": "feedback", "uid_a": "a_1", "updated": "2019-04-30T03:47:14Z"}, {"anon": "stud", "bucket_name": "Week 4/28 - 5/4", "bucket_order": 47, "children": [], "config": {}, "created": "2019-04-30T05:39:19Z", "data": {"embed_links": null}, "folders": [], "id": "jv3d3c2mizz4pj", "subject": "<p>Thanks for the info! I&#39;ll try to plan my schedule around Shewchuk&#39;s 189 then</p>", "tag_good": [], "tag_good_arr": [], "type": "feedback", "uid_a": "a_0", "updated": "2019-04-30T05:39:19Z"}, {"anon": "stud", "bucket_name": "Week 4/28 - 5/4", "bucket_order": 47, "children": [], "config": {}, "created": "2019-04-30T18:32:23Z", "data": {"embed_links": null}, "folders": [], "id": "jv44pil81ok1yv", "subject": "<p>If you have the opportunity, taking 182 maybe pnp\u00a0AFTER 189 with Shewchuk will be a good idea as well!\u00a0</p>", "tag_good": [], "tag_good_arr": [], "type": "feedback", "uid_a": "a_1", "updated": "2019-04-30T18:32:23Z"}], "config": {}, "created": "2019-04-30T03:31:34Z", "data": {"embed_links": null}, "folders": [], "id": "jv38j1pac4t3jq", "no_answer": 0, "no_upvotes": 0, "subject": "<p>I would say\u00a0just take Shewchuk&#39;s 189. I haven&#39;t taken his version of 189, but his seems to be more focused on practical applications. If you&#39;re not interested in the math behind ML/statistics and you won&#39;t be doing research-type work, then I think your time will be better spent on applied classes and projects, instead of taking classes like 126/127. Plus, you&#39;ll probably have more fun doing applied projects, since you said you&#39;re &#34;not too interested in pure ML stuff&#34;.</p>", "tag_good": [], "tag_good_arr": [], "type": "followup", "uid": "ijbyyqoowfj720", "updated": "2019-04-30T03:31:34Z"}], "config": {}, "created": "2019-04-30T03:20:17Z", "data": {"embed_links": []}, "default_anonymity": "no", "drafts": null, "folders": ["enrollments"], "history": [{"anon": "stud", "content": "<p>I&#39;ve read on here before that the recommended &#34;ML track&#34; consists of 126, 127, and 189. I&#39;m not too interested in pure ML stuff (for grad school/research-oriented roles), but I think it&#39;s still important for me to get a general/foundational sense of ML topics (in terms of industry ML-oriented roles) so I know I want to take at least one of these classes.</p>\n<p></p>\n<p>In this case, is it really necessary to take all three of these classes? If not, which one or two are the most recommended for this case?</p>", "created": "2019-04-30T03:20:37Z", "subject": "Which of 126 127 189 are most worth it?", "uid_a": "a_0"}, {"anon": "stud", "content": "<p>I&#39;ve read on here before that the recommended &#34;ML track&#34; consists of 126, 127, and 189. I&#39;m not too interested in pure ML stuff (for grad school/research-oriented roles), but I think it&#39;s still important for me to get a general/foundational sense of ML topics (in terms of industry ML-oriented roles) so I know I want to take at least one of these classes.</p>\n<p></p>\n<p>In this case, is it really necessary to take all three of these classes? If not, which one or two are the most recommended for this case?</p>", "created": "2019-04-30T03:20:18Z", "subject": "Are 126 127 189 worth?", "uid_a": "a_0"}], "i_edits": [], "id": "jv384jt6bzi5wd", "is_bookmarked": false, "is_tag_good": false, "my_favorite": false, "no_answer": 1, "no_answer_followup": 0, "nr": 9440, "num_favorites": 3, "q_edits": [], "request_instructor": 0, "request_instructor_me": false, "s_edits": [], "status": "active", "t": 1654546617623, "tag_good": [], "tag_good_arr": [], "tags": ["enrollments", "student", "unanswered"], "type": "question", "unique_views": 557}